okwt/.mypy_cache/.gitignore
okwt/.mypy_cache/3.11/@plugins_snapshot.json
okwt/.mypy_cache/3.11/PIL/Image.data.json
okwt/.mypy_cache/3.11/PIL/Image.meta.json
okwt/.mypy_cache/3.11/PIL/ImageFilter.data.json
okwt/.mypy_cache/3.11/PIL/ImageFilter.meta.json
okwt/.mypy_cache/3.11/PIL/ImagePalette.data.json
okwt/.mypy_cache/3.11/PIL/ImagePalette.meta.json
okwt/.mypy_cache/3.11/PIL/PyAccess.data.json
okwt/.mypy_cache/3.11/PIL/PyAccess.meta.json
okwt/.mypy_cache/3.11/PIL/__init__.data.json
okwt/.mypy_cache/3.11/PIL/__init__.meta.json
okwt/.mypy_cache/3.11/PIL/_imaging.data.json
okwt/.mypy_cache/3.11/PIL/_imaging.meta.json
okwt/.mypy_cache/3.11/__future__.data.json
okwt/.mypy_cache/3.11/__future__.meta.json
okwt/.mypy_cache/3.11/_ast.data.json
okwt/.mypy_cache/3.11/_ast.meta.json
okwt/.mypy_cache/3.11/_codecs.data.json
okwt/.mypy_cache/3.11/_codecs.meta.json
okwt/.mypy_cache/3.11/_collections_abc.data.json
okwt/.mypy_cache/3.11/_collections_abc.meta.json
okwt/.mypy_cache/3.11/_ctypes.data.json
okwt/.mypy_cache/3.11/_ctypes.meta.json
okwt/.mypy_cache/3.11/_thread.data.json
okwt/.mypy_cache/3.11/_thread.meta.json
okwt/.mypy_cache/3.11/_typeshed/__init__.data.json
okwt/.mypy_cache/3.11/_typeshed/__init__.meta.json
okwt/.mypy_cache/3.11/_warnings.data.json
okwt/.mypy_cache/3.11/_warnings.meta.json
okwt/.mypy_cache/3.11/abc.data.json
okwt/.mypy_cache/3.11/abc.meta.json
okwt/.mypy_cache/3.11/argparse.data.json
okwt/.mypy_cache/3.11/argparse.meta.json
okwt/.mypy_cache/3.11/array.data.json
okwt/.mypy_cache/3.11/array.meta.json
okwt/.mypy_cache/3.11/ast.data.json
okwt/.mypy_cache/3.11/ast.meta.json
okwt/.mypy_cache/3.11/base64.data.json
okwt/.mypy_cache/3.11/base64.meta.json
okwt/.mypy_cache/3.11/builtins.data.json
okwt/.mypy_cache/3.11/builtins.meta.json
okwt/.mypy_cache/3.11/codecs.data.json
okwt/.mypy_cache/3.11/codecs.meta.json
okwt/.mypy_cache/3.11/collections/__init__.data.json
okwt/.mypy_cache/3.11/collections/__init__.meta.json
okwt/.mypy_cache/3.11/collections/abc.data.json
okwt-1.4.4.dist-info/WHEEL
okwt-1.4.4.dist-info/entry_points.txt
okwt-1.4.4.dist-info/METADATA
okwt-1.4.4.dist-info/RECORD
