Metadata-Version: 2.3
Name: okwt
Version: 1.4.4
Summary: Wavetable creation and manipulation tool
Author: Denis Druzhinin
Author-email: Denis Druzhinin <denis@drzhnn.ru>
License: MIT
Classifier: Topic :: File Formats
Classifier: Topic :: Multimedia :: Sound/Audio
Classifier: Topic :: Multimedia :: Sound/Audio :: Conversion
Classifier: Topic :: Multimedia :: Sound/Audio :: Sound Synthesis
Requires-Dist: numpy>=2.0.0
Requires-Dist: pillow>=10.0.0
Requires-Python: >=3.12
